hatch_env_plus/__init__.py
hatch_env_plus/hooks.py
hatch_env_plus/plugin.py
hatch_env_plus-1.0.0.dist-info/METADATA
hatch_env_plus-1.0.0.dist-info/WHEEL
hatch_env_plus-1.0.0.dist-info/entry_points.txt
hatch_env_plus-1.0.0.dist-info/licenses/LICENSE
hatch_env_plus-1.0.0.dist-info/RECORD
