Metadata-Version: 2.4
Name: hatch-env-plus
Version: 1.0.0
Summary: A version source for Hatchling that reads the version from a given environment variable, but also allows for a fallback if the variable is not populated.
Project-URL: homepage, https://github.com/jenskeiner/hatch_env_plus/
Project-URL: repository, https://github.com/jenskeiner/hatch_env_plus.git
Project-URL: documentation, https://github.com/jenskeiner/hatch_env_plus/
Project-URL: issues, https://github.com/jenskeiner/hatch_env_plus/issues
Author-email: Jens Keiner <jens.keiner@gmail.com>
License: Apache-2.0
License-File: LICENSE
Classifier: Development Status :: 4 - Beta
Classifier: Framework :: Hatch
Classifier: Intended Audience :: Developers
Classifier: License :: OSI Approved :: Apache Software License
Classifier: Operating System :: OS Independent
Classifier: Programming Language :: Python
Classifier: Programming Language :: Python :: 3
Classifier: Programming Language :: Python :: 3.10
Classifier: Programming Language :: Python :: 3.11
Classifier: Programming Language :: Python :: 3.12
Classifier: Programming Language :: Python :: 3.13
Classifier: Programming Language :: Python :: 3.14
Classifier: Topic :: Software Development :: Build Tools
Requires-Python: >=3.10
